[{"line":1,"elements":[{"start_timestamp":"2022-12-20T22:18:23.235Z","before":[{"result":{"duration":5000513500,"status":"passed"},"match":{"location":"capstone.framework.base.BaseUITest.setupTests()"}}],"line":20,"name":"Verify department sidebar options","description":"","id":"retail-home-page;verify-department-sidebar-options;;2","after":[{"result":{"duration":1171870300,"status":"passed"},"match":{"location":"capstone.framework.base.BaseUITest.closeTests(io.cucumber.java.Scenario)"}}],"type":"scenario","keyword":"Scenario Outline","steps":[{"result":{"duration":68815400,"status":"passed"},"line":12,"name":"User is on retail website","match":{"location":"capstone.framework.steps.RetailSteps.userIsOnRetailWebsite()"},"keyword":"Given "},{"result":{"duration":4162712300,"status":"passed"},"line":13,"name":"User click on All section","match":{"location":"capstone.framework.steps.RetailSteps.UserClickOnAllSectionBtn()"},"keyword":"When "},{"result":{"duration":153588300,"status":"passed"},"line":14,"name":"User on Electronics","match":{"location":"capstone.framework.steps.RetailSteps.userOnElectronics()"},"keyword":"When "},{"result":{"duration":997900,"status":"passed"},"line":15,"name":"below options are present in department","match":{"location":"capstone.framework.steps.RetailSteps.belowOptionsArePresentInDepartment(io.cucumber.datatable.DataTable)"},"rows":[{"cells":["TV & Video","Video Games"]}],"keyword":"Then "}],"tags":[{"name":"@Test2"}]},{"start_timestamp":"2022-12-20T22:18:33.872Z","before":[{"result":{"duration":4553094800,"status":"passed"},"match":{"location":"capstone.framework.base.BaseUITest.setupTests()"}}],"line":21,"name":"Verify department sidebar options","description":"","id":"retail-home-page;verify-department-sidebar-options;;3","after":[{"result":{"duration":665681600,"status":"passed"},"match":{"location":"capstone.framework.base.BaseUITest.closeTests(io.cucumber.java.Scenario)"}}],"type":"scenario","keyword":"Scenario Outline","steps":[{"result":{"duration":26928200,"status":"passed"},"line":12,"name":"User is on retail website","match":{"location":"capstone.framework.steps.RetailSteps.userIsOnRetailWebsite()"},"keyword":"Given "},{"result":{"duration":4147915700,"status":"passed"},"line":13,"name":"User click on All section","match":{"location":"capstone.framework.steps.RetailSteps.UserClickOnAllSectionBtn()"},"keyword":"When "},{"result":{"duration":4148017500,"status":"passed"},"line":14,"name":"User on Computers","match":{"location":"capstone.framework.steps.RetailSteps.userOnComputers()"},"keyword":"When "},{"result":{"status":"passed"},"line":15,"name":"below options are present in department","match":{"location":"capstone.framework.steps.RetailSteps.belowOptionsArePresentInDepartment(io.cucumber.datatable.DataTable)"},"rows":[{"cells":["Accessories","Networking"]}],"keyword":"Then "}],"tags":[{"name":"@Test2"}]},{"start_timestamp":"2022-12-20T22:18:47.427Z","before":[{"result":{"duration":9766230200,"status":"passed"},"match":{"location":"capstone.framework.base.BaseUITest.setupTests()"}}],"line":22,"name":"Verify department sidebar options","description":"","id":"retail-home-page;verify-department-sidebar-options;;4","after":[{"result":{"duration":776443700,"status":"passed"},"match":{"location":"capstone.framework.base.BaseUITest.closeTests(io.cucumber.java.Scenario)"}}],"type":"scenario","keyword":"Scenario Outline","steps":[{"result":{"duration":27925200,"status":"passed"},"line":12,"name":"User is on retail website","match":{"location":"capstone.framework.steps.RetailSteps.userIsOnRetailWebsite()"},"keyword":"Given "},{"result":{"duration":4163097800,"status":"passed"},"line":13,"name":"User click on All section","match":{"location":"capstone.framework.steps.RetailSteps.UserClickOnAllSectionBtn()"},"keyword":"When "},{"result":{"duration":4157558600,"status":"passed"},"line":14,"name":"User on Smart Home","match":{"location":"capstone.framework.steps.RetailSteps.userOnSmartHome()"},"keyword":"When "},{"result":{"status":"passed"},"line":15,"name":"below options are present in department","match":{"location":"capstone.framework.steps.RetailSteps.belowOptionsArePresentInDepartment(io.cucumber.datatable.DataTable)"},"rows":[{"cells":["Smart Home Lightning","Plugs and Outlets"]}],"keyword":"Then "}],"tags":[{"name":"@Test2"}]},{"start_timestamp":"2022-12-20T22:19:06.329Z","before":[{"result":{"duration":3054627500,"status":"passed"},"match":{"location":"capstone.framework.base.BaseUITest.setupTests()"}}],"line":23,"name":"Verify department sidebar options","description":"","id":"retail-home-page;verify-department-sidebar-options;;5","after":[{"result":{"duration":648033000,"status":"passed"},"match":{"location":"capstone.framework.base.BaseUITest.closeTests(io.cucumber.java.Scenario)"}}],"type":"scenario","keyword":"Scenario Outline","steps":[{"result":{"duration":36900600,"status":"passed"},"line":12,"name":"User is on retail website","match":{"location":"capstone.framework.steps.RetailSteps.userIsOnRetailWebsite()"},"keyword":"Given "},{"result":{"duration":4159107600,"status":"passed"},"line":13,"name":"User click on All section","match":{"location":"capstone.framework.steps.RetailSteps.UserClickOnAllSectionBtn()"},"keyword":"When "},{"result":{"duration":4140795900,"status":"passed"},"line":14,"name":"User on Sports","match":{"location":"capstone.framework.steps.RetailSteps.userOnSports()"},"keyword":"When "},{"result":{"status":"passed"},"line":15,"name":"below options are present in department","match":{"location":"capstone.framework.steps.RetailSteps.belowOptionsArePresentInDepartment(io.cucumber.datatable.DataTable)"},"rows":[{"cells":["Athletic Clothing","Exercise & Fitness"]}],"keyword":"Then "}],"tags":[{"name":"@Test2"}]},{"start_timestamp":"2022-12-20T22:19:18.379Z","before":[{"result":{"duration":3505123800,"status":"passed"},"match":{"location":"capstone.framework.base.BaseUITest.setupTests()"}}],"line":24,"name":"Verify department sidebar options","description":"","id":"retail-home-page;verify-department-sidebar-options;;6","after":[{"result":{"duration":684110900,"status":"passed"},"match":{"location":"capstone.framework.base.BaseUITest.closeTests(io.cucumber.java.Scenario)"}}],"type":"scenario","keyword":"Scenario Outline","steps":[{"result":{"duration":28923500,"status":"passed"},"line":12,"name":"User is on retail website","match":{"location":"capstone.framework.steps.RetailSteps.userIsOnRetailWebsite()"},"keyword":"Given "},{"result":{"duration":4130032100,"status":"passed"},"line":13,"name":"User click on All section","match":{"location":"capstone.framework.steps.RetailSteps.UserClickOnAllSectionBtn()"},"keyword":"When "},{"result":{"duration":4143337700,"status":"passed"},"line":14,"name":"User on Automotive","match":{"location":"capstone.framework.steps.RetailSteps.userOnAutomotive()"},"keyword":"When "},{"result":{"duration":997300,"status":"passed"},"line":15,"name":"below options are present in department","match":{"location":"capstone.framework.steps.RetailSteps.belowOptionsArePresentInDepartment(io.cucumber.datatable.DataTable)"},"rows":[{"cells":["Automative Parts & Accessories","MotorCycle & Powersports"]}],"keyword":"Then "}],"tags":[{"name":"@Test2"}]}],"name":"Retail Home Page","description":"","id":"retail-home-page","keyword":"Feature","uri":"classpath:features/RetailHomePage.feature","tags":[]}]